plct_cli/__init__.py
plct_cli/__main__.py
plct_cli/cli.py
plct_cli/project_config.py
plct_cli-0.0.5.dist-info/entry_points.txt
plct_cli-0.0.5.dist-info/LICENSE
plct_cli-0.0.5.dist-info/METADATA
plct_cli-0.0.5.dist-info/WHEEL
plct_cli-0.0.5.dist-info/RECORD
