Metadata-Version: 2.1
Name: plct-cli
Version: 0.0.5
Summary: Command line interface for working with Sphinx projects.
Author: Petlja
Author-email: loop@petlja.com
Classifier: Programming Language :: Python :: 2
Classifier: Programming Language :: Python :: 2.7
Classifier: Programming Language :: Python :: 3
Classifier: Programming Language :: Python :: 3.4
Classifier: Programming Language :: Python :: 3.5
Classifier: Programming Language :: Python :: 3.6
Classifier: Programming Language :: Python :: 3.7
Classifier: Programming Language :: Python :: 3.8
Classifier: Programming Language :: Python :: 3.9
Classifier: Programming Language :: Python :: 3.10
Classifier: Programming Language :: Python :: 3.11
Classifier: Programming Language :: Python :: 3.12
Requires-Dist: PyYAML
Requires-Dist: Sphinx (==7.1.2)
Requires-Dist: click
Requires-Dist: paver
Requires-Dist: plct-bulder-for-sphinx
Requires-Dist: sphinx-autobuild
